KratosMultiphysics/ShapeOptimizationApplication/TemplateMainKratosShapeOptimization.py
KratosMultiphysics/ShapeOptimizationApplication/__init__.py
KratosMultiphysics/ShapeOptimizationApplication/communicator_factory.py
KratosMultiphysics/ShapeOptimizationApplication/mapper_factory.py
KratosMultiphysics/ShapeOptimizationApplication/model_part_controller_factory.py
KratosMultiphysics/ShapeOptimizationApplication/optimizer_factory.py
KratosMultiphysics/ShapeOptimizationApplication/algorithms/__init__.py
KratosMultiphysics/ShapeOptimizationApplication/algorithms/algorithm_base.py
KratosMultiphysics/ShapeOptimizationApplication/algorithms/algorithm_bead_optimization.py
KratosMultiphysics/ShapeOptimizationApplication/algorithms/algorithm_factory.py
KratosMultiphysics/ShapeOptimizationApplication/algorithms/algorithm_gradient_projection.py
KratosMultiphysics/ShapeOptimizationApplication/algorithms/algorithm_penalized_projection.py
KratosMultiphysics/ShapeOptimizationApplication/algorithms/algorithm_relaxed_gradient_projection.py
KratosMultiphysics/ShapeOptimizationApplication/algorithms/algorithm_shape_fraction_optimization.py
KratosMultiphysics/ShapeOptimizationApplication/algorithms/algorithm_steepest_descent.py
KratosMultiphysics/ShapeOptimizationApplication/algorithms/algorithm_trust_region.py
KratosMultiphysics/ShapeOptimizationApplication/analyzers/__init__.py
KratosMultiphysics/ShapeOptimizationApplication/analyzers/analyzer_base.py
KratosMultiphysics/ShapeOptimizationApplication/analyzers/analyzer_empty.py
KratosMultiphysics/ShapeOptimizationApplication/analyzers/analyzer_factory.py
KratosMultiphysics/ShapeOptimizationApplication/analyzers/analyzer_internal.py
KratosMultiphysics/ShapeOptimizationApplication/custom_ios/__init__.py
KratosMultiphysics/ShapeOptimizationApplication/custom_ios/wrl_io.py
KratosMultiphysics/ShapeOptimizationApplication/custom_ios/wrl_reader.py
KratosMultiphysics/ShapeOptimizationApplication/loggers/__init__.py
kratosshapeoptimizationapplication-10.4.0.dist-info/METADATA
kratosshapeoptimizationapplication-10.4.0.dist-info/WHEEL
kratosshapeoptimizationapplication-10.4.0.dist-info/RECORD
